bgserve/__init__.py
bgserve/_background_server.py
bgserve/_protocols.py
bgserve/_provide.py
bgserve/_resources.py
bgserve/_tilesets.py
bgserve/_util.py
bgserve-0.0.1.dist-info/METADATA
bgserve-0.0.1.dist-info/WHEEL
bgserve-0.0.1.dist-info/licenses/LICENSE
bgserve-0.0.1.dist-info/RECORD
