Metadata-Version: 2.1
Name: bgserve
Version: 0.0.1
Summary: an extensible async background server
Project-URL: Documentation, https://github.com/unknown/bgserve#readme
Project-URL: Issues, https://github.com/unknown/bgserve/issues
Project-URL: Source, https://github.com/unknown/bgserve
Author-email: Trevor Manz <trevor.j.manz@gmail.com>
License: MIT
License-File: LICENSE
Classifier: Development Status :: 4 - Beta
Classifier: Programming Language :: Python
Classifier: Programming Language :: Python :: 3.8
Classifier: Programming Language :: Python :: 3.9
Classifier: Programming Language :: Python :: 3.10
Classifier: Programming Language :: Python :: 3.11
Classifier: Programming Language :: Python :: Implementation :: CPython
Classifier: Programming Language :: Python :: Implementation :: PyPy
Requires-Python: >=3.8
Requires-Dist: portpicker
Requires-Dist: starlette>=0.26.1
Requires-Dist: uvicorn>=0.21.1
